Cache.v
module Cache(clk, Address, Data_Out, Hit_Miss);
	input wire [31:0] Address; 			//the input address that is given
	input clk; 					//clk for syncheonization
	output reg [31:0] Data_Out; 			//for the data that will be returned from cache
	output reg Hit_Miss; 				//set if there is a hit else 0 for miss
    
    	reg [15:0] [31:0] Cache_Memory[255:0]; 		//a memory of registers 256 x 16 words ,where 1 word is 32 bits.
    	reg [17:0] Cache_Tags[255:0]; 			//a set of registers for the tag bits
	reg [7:0] memory[0:32763]; 			// the main memory

	//set of registers used for storing parts of the addess like tag bits,
	// index bits etc. for ease of working.
    	reg [17:0] Tag_Bits; 				 
    	reg [7:0] Index_Bits; 				
    	reg [3:0] Byte_Offset; 			
    	reg [31:0] M; 
	//set of temporary registers required for future purposes
	reg [31:0]temp; 		
	reg [31:0]temp2; 			
	reg [31:0]temp3; 		
	integer i;
	integer j;
	integer count;
	//this reads the data into the actual main memory from the file
	//"memory.list"
	initial begin
		$readmemb("memory.list",memory);	
		count = 0;
	end
	//Here in this block we seperate the address to tag bits , index bits
	//etc. and then check for the address in the cache .Incase of a miss
	//we proceed to the next block
	always@(posedge clk)
    	begin
	        Tag_Bits = Address[31:14];
        	Index_Bits = Address[13:6];
	        Byte_Offset = Address[5:2];
		count+=1;
    		M = 32'b0000_0000_0000_0000_0000_0000_0000_1111;
        	if(Cache_Tags[Index_Bits] == Tag_Bits)
        	begin
			Hit_Miss = 1;
        	    	Data_Out = Cache_Memory[Index_Bits][Byte_Offset];
		end
        	else
        	begin
            		Hit_Miss = 0;
        	end
    	end
    	//This is the code for getting the block of data if there is a cache miss. 
    	//here we are anding with the a given numebr to make the last 6 bits
	//0 and start from the firt location of the required bloack of data. 
	always@(posedge clk)
    	begin
		if(Hit_Miss == 0)
		begin
			count+=1;
			temp3 = Address & 32'b11111111_11111111_11111111_11000000;
			for(i=0;i<16;i++)
			begin
				temp = 0;
				temp = temp | temp3;
				temp3 = temp3+4;
				for(j=0;j<4;j++)
				begin
					temp2 = temp2<<8;
					temp2 = memory[temp+j];
				end
				//Assigning the data in the memory 
				Cache_Memory[Index_Bits][i] = temp2;
			end
			Cache_Tags[Index_Bits] <= Address[31:14];
    		end
	end
endmodule

Cache_tb.v
module cache_tb;
	reg clk;
	reg [31:0]Address;
	wire [31:0]Data_Out;
	wire Hit_Miss;
	Cache uut(
		.clk(clk),
		.Data_Out(Data_Out),
		.Address(Address),
		.Hit_Miss(Hit_Miss)
	);
	initial begin
		$dumpfile("cache.vcd");
		$dumpvars(0,cache_tb);
		clk = 0;
		$display("Direct Mapped Cache");
		$display("---------------------------------------------------------------------\n");
		Address = 32'b0000_0000_0000_0000_0000_0000_0000_1000;
		#30;
		$display("Hit=%b Data=%h address=%h\n",Hit_Miss,Data_Out,Address);
		#5;
		Address = 32'b0000_0000_0000_0000_0000_0000_0000_1100;
		#5;
		$display("Hit=%b Data=%h address=%h\n",Hit_Miss,Data_Out,Address);

	end
	initial begin
	repeat(50)#5 clk = ~clk;
end
endmodule

cache.vcd
$date
	Fri Nov 23 21:22:08 2018
$end
$version
	Icarus Verilog
$end
$timescale
	1s
$end
$scope module cache_tb $end
$var wire 1 ! Hit_Miss $end
$var wire 32 " Data_Out [31:0] $end
$var reg 32 # Address [31:0] $end
$var reg 1 $ clk $end
$scope module uut $end
$var wire 32 % Address [31:0] $end
$var wire 1 $ clk $end
$var reg 4 & Byte_Offset [3:0] $end
$var reg 32 ' Data_Out [31:0] $end
$var reg 1 ! Hit_Miss $end
$var reg 8 ( Index_Bits [7:0] $end
$var reg 32 ) M [31:0] $end
$var reg 18 * Tag_Bits [17:0] $end
$var reg 32 + temp [31:0] $end
$var reg 32 , temp2 [31:0] $end
$var reg 32 - temp3 [31:0] $end
$var integer 32 . count [31:0] $end
$var integer 32 / i [31:0] $end
$var integer 32 0 j [31:0] $end
$upscope $end
$upscope $end
$enddefinitions $end
#0
$dumpvars
bx 0
bx /
b0 .
bx -
bx ,
bx +
bx *
bx )
bx (
bx '
bx &
b1000 %
0$
b1000 #
bx "
x!
$end
#5
0!
b1111 )
b1 .
b10 &
b0 (
b0 *
1$
#10
0$
#15
b1111 ,
b100 0
b111100 +
b10000 /
b1000000 -
b11 .
1$
#20
0$
#25
b10 "
b10 '
1!
b1111 ,
b100 0
b111100 +
b10000 /
b1000000 -
b101 .
1$
#30
0$
#35
b11 "
b11 '
b110 .
b11 &
1$
b1100 #
b1100 %
#40
0$
#45
b111 .
1$
#50
0$
#55
b1000 .
1$
#60
0$
#65
b1001 .
1$
#70
0$
#75
b1010 .
1$
#80
0$
#85
b1011 .
1$
#90
0$
#95
b1100 .
1$
#100
0$
#105
b1101 .
1$
#110
0$
#115
b1110 .
1$
#120
0$
#125
b1111 .
1$
#130
0$
#135
b10000 .
1$
#140
0$
#145
b10001 .
1$
#150
0$
#155
b10010 .
1$
#160
0$
#165
b10011 .
1$
#170
0$
#175
b10100 .
1$
#180
0$
#185
b10101 .
1$
#190
0$
#195
b10110 .
1$
#200
0$
#205
b10111 .
1$
#210
0$
#215
b11000 .
1$
#220
0$
#225
b11001 .
1$
#230
0$
#235
b11010 .
1$
#240
0$
#245
b11011 .
1$
